swarmauri_core/ComponentBase.py
swarmauri_core/README.md
swarmauri_core/__init__.py
swarmauri_core/agent_apis/IAgentCommands.py
swarmauri_core/agent_apis/IAgentRouterCRUD.py
swarmauri_core/agent_apis/__init__.py
swarmauri_core/agent_factories/IExportConf.py
swarmauri_core/agent_factories/__init__.py
swarmauri_core/agents/IAgent.py
swarmauri_core/agents/IAgentConversation.py
swarmauri_core/agents/IAgentParser.py
swarmauri_core/agents/IAgentRetrieve.py
swarmauri_core/agents/IAgentSystemContext.py
swarmauri_core/agents/IAgentToolkit.py
swarmauri_core/agents/IAgentVectorStore.py
swarmauri_core/agents/__init__.py
swarmauri_core/chains/ICallableChain.py
swarmauri_core/chains/IChain.py
swarmauri_core/chains/IChainContext.py
swarmauri_core/chains/IChainContextLoader.py
swarmauri_core/chains/IChainDependencyResolver.py
swarmauri_core/chains/IChainFactory.py
swarmauri_core/chains/IChainStep.py
swarmauri_core/chains/__init__.py
swarmauri_core/chunkers/IChunker.py
swarmauri_core/chunkers/__init__.py
swarmauri_core/control_panels/IControlPanel.py
swarmauri_core/control_panels/__init__.py
swarmauri_core/conversations/IConversation.py
swarmauri_core/conversations/IMaxSize.py
swarmauri_core/conversations/ISystemContext.py
swarmauri_core/conversations/__init__.py
swarmauri_core/dataconnectors/IDataConnector.py
swarmauri_core/dataconnectors/__init__.py
swarmauri_core/distances/IDistanceSimilarity.py
swarmauri_core/distances/__init__.py
swarmauri_core/document_stores/IDocumentRetrieve.py
swarmauri_core/document_stores/IDocumentStore.py
swarmauri_core/document_stores/__init__.py
swarmauri_core/documents/IDocument.py
swarmauri_core/documents/IExperimentDocument.py
swarmauri_core/documents/__init__.py
swarmauri_core/embeddings/IFeature.py
swarmauri_core/embeddings/ISaveModel.py
swarmauri_core/embeddings/IVectorize.py
swarmauri_core/embeddings/__init__.py
swarmauri_core/evaluator_pools/IEvaluatorPool.py
swarmauri_core/evaluator_pools/__init__.py
swarmauri_core-0.7.5.dist-info/LICENSE
swarmauri_core-0.7.5.dist-info/METADATA
swarmauri_core-0.7.5.dist-info/WHEEL
swarmauri_core-0.7.5.dist-info/RECORD
